anki_mac_helper/__init__.py
anki_mac_helper/libankihelper.dylib
anki_mac_helper/py.typed
anki_mac_helper-0.1.0.dist-info/METADATA
anki_mac_helper-0.1.0.dist-info/WHEEL
anki_mac_helper-0.1.0.dist-info/RECORD
